elastic_feeder/__init__.py
elastic_feeder/controller.py
elastic_feeder/csv_reader.py
elastic_feeder/elastic.py
elastic_feeder/exception.py
elastic_feeder/helper.py
elastic_feeder/scripts/__init__.py
elastic_feeder/scripts/commands.py
elasticfeed-0.1.1.dist-info/LICENSE
elasticfeed-0.1.1.dist-info/METADATA
elasticfeed-0.1.1.dist-info/WHEEL
elasticfeed-0.1.1.dist-info/entry_points.txt
elasticfeed-0.1.1.dist-info/top_level.txt
elasticfeed-0.1.1.dist-info/RECORD
