Metadata-Version: 2.1
Name: elasticfeed
Version: 0.1.1
Summary: Export csv data into Elasticsearch
Home-page: https://github.com/AliyevH/elk_feeder
Author: Hasan Aliyev
Author-email: hasan.aliyev.555@gmail.com
License: MIT
Platform: UNKNOWN
Classifier: Intended Audience :: Developers
Classifier: Topic :: Software Development :: Build Tools
Classifier: License :: OSI Approved :: MIT License
Classifier: Programming Language :: Python
Classifier: Programming Language :: Python :: 3
Classifier: Programming Language :: Python :: 3.6
Classifier: Programming Language :: Python :: 3.7
Classifier: Programming Language :: Python :: 3 :: Only
Classifier: License :: OSI Approved :: MIT License
Classifier: Operating System :: OS Independent
Requires-Dist: click
Requires-Dist: elasticsearch
